lunar_interceptor/__init__.py
lunar_interceptor/py.typed
lunar_interceptor/interceptor/__init__.py
lunar_interceptor/interceptor/configuration.py
lunar_interceptor/interceptor/fail_safe.py
lunar_interceptor/interceptor/helpers.py
lunar_interceptor/interceptor/interceptor.py
lunar_interceptor/interceptor/singleton.py
lunar_interceptor/interceptor/traffic_filter.py
lunar_interceptor/interceptor/hooks/__init__.py
lunar_interceptor/interceptor/hooks/aiohttp.py
lunar_interceptor/interceptor/hooks/const.py
lunar_interceptor/interceptor/hooks/helpers.py
lunar_interceptor/interceptor/hooks/hook.py
lunar_interceptor/interceptor/hooks/requests.py
lunar_interceptor-0.3.4.dist-info/METADATA
lunar_interceptor-0.3.4.dist-info/WHEEL
lunar_interceptor-0.3.4.dist-info/top_level.txt
lunar_interceptor-0.3.4.dist-info/RECORD
